pvporcupine/LICENSE
pvporcupine/__init__.py
pvporcupine/_factory.py
pvporcupine/_porcupine.py
pvporcupine/_util.py
pvporcupine/lib/beaglebone/libpv_porcupine.so
pvporcupine/lib/common/porcupine_params.pv
pvporcupine/lib/jetson/cortex-a57-aarch64/libpv_porcupine.so
pvporcupine/lib/linux/x86_64/libpv_porcupine.so
pvporcupine/lib/mac/arm64/libpv_porcupine.dylib
pvporcupine/lib/mac/x86_64/libpv_porcupine.dylib
pvporcupine/lib/raspberry-pi/arm11/libpv_porcupine.so
pvporcupine/lib/raspberry-pi/cortex-a53/libpv_porcupine.so
pvporcupine/lib/raspberry-pi/cortex-a53-aarch64/libpv_porcupine.so
pvporcupine/lib/raspberry-pi/cortex-a7/libpv_porcupine.so
pvporcupine/lib/raspberry-pi/cortex-a72/libpv_porcupine.so
pvporcupine/lib/raspberry-pi/cortex-a72-aarch64/libpv_porcupine.so
pvporcupine/lib/windows/amd64/libpv_porcupine.dll
pvporcupine/resources/keyword_files/beaglebone/alexa_beaglebone.ppn
pvporcupine/resources/keyword_files/beaglebone/americano_beaglebone.ppn
pvporcupine/resources/keyword_files/beaglebone/blueberry_beaglebone.ppn
pvporcupine/resources/keyword_files/beaglebone/bumblebee_beaglebone.ppn
pvporcupine/resources/keyword_files/beaglebone/computer_beaglebone.ppn
pvporcupine/resources/keyword_files/beaglebone/grapefruit_beaglebone.ppn
pvporcupine/resources/keyword_files/beaglebone/grasshopper_beaglebone.ppn
pvporcupine/resources/keyword_files/beaglebone/hey barista_beaglebone.ppn
pvporcupine/resources/keyword_files/beaglebone/hey google_beaglebone.ppn
pvporcupine/resources/keyword_files/beaglebone/hey siri_beaglebone.ppn
pvporcupine/resources/keyword_files/beaglebone/jarvis_beaglebone.ppn
pvporcupine/resources/keyword_files/beaglebone/ok google_beaglebone.ppn
pvporcupine/resources/keyword_files/beaglebone/pico clock_beaglebone.ppn
pvporcupine/resources/keyword_files/beaglebone/picovoice_beaglebone.ppn
pvporcupine/resources/keyword_files/beaglebone/porcupine_beaglebone.ppn
pvporcupine/resources/keyword_files/beaglebone/terminator_beaglebone.ppn
pvporcupine-3.0.0.dist-info/METADATA
pvporcupine-3.0.0.dist-info/WHEEL
pvporcupine-3.0.0.dist-info/top_level.txt
pvporcupine-3.0.0.dist-info/RECORD
