Metadata-Version: 2.1
Name: pvporcupine
Version: 3.0.0
Summary: Porcupine wake word engine.
Home-page: https://github.com/Picovoice/porcupine
Author: Picovoice
Author-email: hello@picovoice.ai
License: UNKNOWN
Keywords: wake word engine,hotword detection,keyword spotting,wake word detection,voice commands
Platform: UNKNOWN
Classifier: Development Status :: 5 - Production/Stable
Classifier: Intended Audience :: Developers
Classifier: License :: OSI Approved :: Apache Software License
Classifier: Operating System :: OS Independent
Classifier: Programming Language :: Python :: 3
Classifier: Topic :: Multimedia :: Sound/Audio :: Speech
Requires-Python: >=3.5
